{"reaveau01": {"name": "Austin Reaves", "object": null}, "vincega01": {"name": "Gabe Vincent", "object": null}, "jamesle01": {"name": "LeBron James", "object": null}, "hachiru01": {"name": "Rui Hachimura", "object": null}, "hayesja02": {"name": "Jaxson Hayes", "object": null}, "chrisma02": {"name": "Max Christie", "object": null}, "davisan02": {"name": "Anthony Davis", "object": null}, "finnedo01": {"name": "Dorian Finney-Smith", "object": null}, "kolokch01": {"name": "Christian Koloko", "object": null}, "reddica01": {"name": "Cam Reddish", "object": null}, "vandeja01": {"name": "Jarred Vanderbilt", "object": null}, "russeda01": {"name": "D'Angelo Russell", "object": null}, "miltosh01": {"name": "Shake Milton", "object": null}, "jamesbr02": {"name": "Bronny James", "object": null}, "doncilu01": {"name": "Luka Don\u010di\u0107", "object": null}, "goodwjo01": {"name": "Jordan Goodwin", "object": null}, "jemistr01": {"name": "Trey Jemison", "object": null}, "lenal01": {"name": "Alex Len", "object": null}, "armeltr01": {"name": "Armel Traor\u00e9", "object": null}, "lewisma05": {"name": "Maxwell Lewis", "object": null}, "morrima02": {"name": "Markieff Morris", "object": null}, "olivaqu01": {"name": "Quincy Olivari", "object": null}, "hoodsja01": {"name": "Jalen Hood-Schifino", "object": null}}