{"conlemi01": {"name": "Mike Conley", "object": null}, "gasolma01": {"name": "Marc Gasol", "object": null}, "allento01": {"name": "Tony Allen", "object": null}, "patteru01": {"name": "Ruben Patterson", "object": null}, "cartevi01": {"name": "Vince Carter", "object": null}, "stoudda01": {"name": "Damon Stoudamire", "object": null}, "koufoko01": {"name": "Kosta Koufos", "object": null}, "gayru01": {"name": "Rudy Gay", "object": null}, "davisda01": {"name": "Dale Davis", "object": null}, "mayooj01": {"name": "O.J. Mayo", "object": null}, "anderde01": {"name": "Derek Anderson", "object": null}, "arthuda01": {"name": "Darrell Arthur", "object": null}, "leeco01": {"name": "Courtney Lee", "object": null}, "youngsa01": {"name": "Sam Young", "object": null}, "greenja01": {"name": "JaMychal Green", "object": null}, "wallara01": {"name": "Rasheed Wallace", "object": null}, "outlatr01": {"name": "Travis Outlaw", "object": null}, "princta01": {"name": "Tayshaun Prince", "object": null}, "pondequ01": {"name": "Quincy Pondexter", "object": null}, "przybjo01": {"name": "Joel Przybilla", "object": null}, "jackja01": {"name": "Jarrett Jack", "object": null}, "calatni01": {"name": "Nick Calathes", "object": null}, "wellsbo01": {"name": "Bonzi Wells", "object": null}, "ratlith01": {"name": "Theo Ratliff", "object": null}, "leuerjo01": {"name": "Jon Leuer", "object": null}, "dixonju01": {"name": "Juan Dixon", "object": null}, "webstma02": {"name": "Martell Webster", "object": null}, "bayleje01": {"name": "Jerryd Bayless", "object": null}, "milesda01": {"name": "Darius Miles", "object": null}, "mcinnje01": {"name": "Jeff McInnis", "object": null}, "woodsqy01": {"name": "Qyntel Woods", "object": null}, "thabeha01": {"name": "Hasheem Thabeet", "object": null}, "davised01": {"name": "Ed Davis", "object": null}, "udrihbe01": {"name": "Beno Udrih", "object": null}, "greenje02": {"name": "Jeff Green", "object": null}, "haddaha01": {"name": "Hamed Haddadi", "object": null}, "telfase01": {"name": "Sebastian Telfair", "object": null}, "pippesc01": {"name": "Scottie Pippen", "object": null}, "jonesfr01": {"name": "Fred Jones", "object": null}, "millemi01": {"name": "Mike Miller", "object": null}, "sabonar01": {"name": "Arvydas Sabonis", "object": null}, "leeda02": {"name": "David Lee", "object": null}, "vasqugr01": {"name": "Greivis V\u00e1squez", "object": null}, "crawfja01": {"name": "Jamal Crawford", "object": null}, "ennisja01": {"name": "James Ennis III", "object": null}, "carrode01": {"name": "DeMarre Carroll", "object": null}, "robinna01": {"name": "Nate Robinson", "object": null}, "harrian01": {"name": "Andrew Harrison", "object": null}, "speigma01": {"name": "Marreese Speights", "object": null}, "daniean01": {"name": "Antonio Daniels", "object": null}, "collima01": {"name": "Mardy Collins", "object": null}, "richaqu01": {"name": "Quentin Richardson", "object": null}, "barnema02": {"name": "Matt Barnes", "object": null}, "udokaim01": {"name": "Ime Udoka", "object": null}, "magloja01": {"name": "Jamaal Magloire", "object": null}, "khryavi01": {"name": "Viktor Khryapa", "object": null}, "danietr01": {"name": "Troy Daniels", "object": null}, "blakest01": {"name": "Steve Blake", "object": null}, "jeffrja01": {"name": "Jared Jeffries", "object": null}, "willima03": {"name": "Marcus Williams", "object": null}, "aldrila01": {"name": "LaMarcus Aldridge", "object": null}, "hieldbu01": {"name": "Buddy Hield", "object": null}, "abdursh01": {"name": "Shareef Abdur-Rahim", "object": null}, "martija01": {"name": "Jarell Martin", "object": null}, "dickada01": {"name": "Dan Dickau", "object": null}, "balkmre01": {"name": "Renaldo Balkman", "object": null}, "bogdabo01": {"name": "Bogdan Bogdanovi\u0107", "object": null}, "johnsja01": {"name": "James Johnson", "object": null}, "templga01": {"name": "Garrett Temple", "object": null}, "rodrise01": {"name": "Sergio Rodr\u00edguez", "object": null}, "foxde01": {"name": "De'Aaron Fox", "object": null}, "caulewi01": {"name": "Willie Cauley-Stein", "object": null}, "curryed01": {"name": "Eddy Curry", "object": null}, "chalmma01": {"name": "Mario Chalmers", "object": null}, "roybr01": {"name": "Brandon Roy", "object": null}, "jacksju01": {"name": "Justin Jackson", "object": null}, "rosema01": {"name": "Malik Rose", "object": null}, "vanexni01": {"name": "Nick Van Exel", "object": null}, "stepavl01": {"name": "Vladimir Stepania", "object": null}, "labissk01": {"name": "Skal Labissi\u00e8re", "object": null}, "skinnbr01": {"name": "Brian Skinner", "object": null}, "wrighbr03": {"name": "Brandan Wright", "object": null}, "hillge01": {"name": "George Hill", "object": null}, "kempsh01": {"name": "Shawn Kemp", "object": null}, "ellinwa01": {"name": "Wayne Ellington", "object": null}, "tinslja01": {"name": "Jamaal Tinsley", "object": null}, "gordoer01": {"name": "Eric Gordon", "object": null}, "masonfr01": {"name": "Frank Mason III", "object": null}, "wroteto01": {"name": "Tony Wroten", "object": null}, "chandwi01": {"name": "Wilson Chandler", "object": null}, "kerrst01": {"name": "Steve Kerr", "object": null}, "davisba01": {"name": "Baron Davis", "object": null}, "henryxa01": {"name": "Xavier Henry", "object": null}, "novakst01": {"name": "Steve Novak", "object": null}, "battish01": {"name": "Shane Battier", "object": null}, "thornal01": {"name": "Al Thornton", "object": null}, "brunsri01": {"name": "Rick Brunson", "object": null}, "cunnida01": {"name": "Dante Cunningham", "object": null}, "persowe01": {"name": "Wesley Person", "object": null}, "parsoch01": {"name": "Chandler Parsons", "object": null}, "davisde01": {"name": "Deyonta Davis", "object": null}, "dayeau01": {"name": "Austin Daye", "object": null}, "cambyma01": {"name": "Marcus Camby", "object": null}, "taylomi01": {"name": "Mike Taylor", "object": null}, "baldwwa01": {"name": "Wade Baldwin", "object": null}, "adamsjo01": {"name": "Jordan Adams", "object": null}, "boumtru01": {"name": "Ruben Boumtje-Boumtje", "object": null}, "seungha01": {"name": "Ha Seung-Jin", "object": null}, "smithch04": {"name": "Charles Smith", "object": null}, "jordade01": {"name": "DeAndre Jordan", "object": null}, "moniase01": {"name": "Sergei Monia", "object": null}, "holliry01": {"name": "Ryan Hollins", "object": null}, "anderch01": {"name": "Chris Andersen", "object": null}, "arenagi01": {"name": "Gilbert Arenas", "object": null}, "douglto01": {"name": "Toney Douglas", "object": null}, "stephla01": {"name": "Lance Stephenson", "object": null}, "frankja01": {"name": "Jamaal Franklin", "object": null}, "dudlech02": {"name": "Chris Dudley", "object": null}, "richama01": {"name": "Malachi Richardson", "object": null}, "doolike01": {"name": "Keyon Dooling", "object": null}, "marbust01": {"name": "Stephon Marbury", "object": null}, "huntest01": {"name": "Steven Hunter", "object": null}, "gilled01": {"name": "Eddie Gill", "object": null}, "smithru01": {"name": "Russ Smith", "object": null}, "selbyjo01": {"name": "Josh Selby", "object": null}, "smithis01": {"name": "Ish Smith", "object": null}, "powele01": {"name": "Leon Powe", "object": null}, "pargoje01": {"name": "Jeremy Pargo", "object": null}, "willitr02": {"name": "Troy Williams", "object": null}, "lafrera01": {"name": "Raef LaFrentz", "object": null}, "seldewa01": {"name": "Wayne Selden", "object": null}, "cookom01": {"name": "Omar Cook", "object": null}, "hairspj02": {"name": "P.J. Hairston", "object": null}, "munfoxa02": {"name": "Xavier Munford", "object": null}, "stokeja01": {"name": "Jarnell Stokes", "object": null}, "farmajo01": {"name": "Jordan Farmar", "object": null}, "grahast01": {"name": "Stephen Graham", "object": null}, "frahmri01": {"name": "Richie Frahm", "object": null}, "davispa01": {"name": "Paul Davis", "object": null}, "hartja01": {"name": "Jason Hart", "object": null}, "carroma01": {"name": "Matt Carroll", "object": null}, "sampsja02": {"name": "JaKarr Sampson", "object": null}, "kamanch01": {"name": "Chris Kaman", "object": null}, "barkler01": {"name": "Erick Barkley", "object": null}, "morrira01": {"name": "Randolph Morris", "object": null}, "hudsole01": {"name": "Lester Hudson", "object": null}, "duhonch01": {"name": "Chris Duhon", "object": null}, "lenarvo01": {"name": "Voshon Lenard", "object": null}, "papagge01": {"name": "Georgios Papagiannis", "object": null}, "davisri01": {"name": "Ricky Davis", "object": null}, "willija02": {"name": "Jason Williams", "object": null}, "ackeral01": {"name": "Alex Acker", "object": null}, "johnsch04": {"name": "Chris Johnson", "object": null}, "murratr01": {"name": "Tracy Murray", "object": null}, "roberan02": {"name": "Anthony Roberson", "object": null}, "lawac01": {"name": "Acie Law", "object": null}, "fergude01": {"name": "Desmond Ferguson", "object": null}, "butlemi02": {"name": "Mitchell Butler", "object": null}, "carlige01": {"name": "Geno Carlisle", "object": null}, "brewero02": {"name": "Ronnie Brewer", "object": null}, "williel01": {"name": "Elliot Williams", "object": null}, "cottobr01": {"name": "Bryce Cotton", "object": null}, "morrida01": {"name": "Darius Morris", "object": null}, "pittmde01": {"name": "Dexter Pittman", "object": null}, "thomaja02": {"name": "James Thomas", "object": null}, "mccalra01": {"name": "Ray McCallum", "object": null}, "davisjo02": {"name": "Josh Davis", "object": null}, "cabocbr01": {"name": "Bruno Caboclo", "object": null}, "iversal01": {"name": "Allen Iverson", "object": null}, "dickeka01": {"name": "Kaniel Dickens", "object": null}, "gallida01": {"name": "Danilo Gallinari", "object": null}, "jamesje01": {"name": "Jerome James", "object": null}, "carnero01": {"name": "Rodney Carney", "object": null}, "sambch01": {"name": "Cheikh Samb", "object": null}, "gildetr01": {"name": "Trey Gilder", "object": null}, "thomaty01": {"name": "Tyrus Thomas", "object": null}, "lucaska01": {"name": "Kalin Lucas", "object": null}, "vranesl01": {"name": "Slavko Vrane\u0161", "object": null}, "richaje01": {"name": "Jeremy Richardson", "object": null}, "weberbr01": {"name": "Briante Weber", "object": null}, "cooleja01": {"name": "Jack Cooley", "object": null}, "curryse01": {"name": "Seth Curry", "object": null}}